autoBoostcamp/__init__.py
autoBoostcamp/__main__.py
autoBoostcamp/backend.py
autoBoostcamp/test.py
autoBoostcamp-10.0.dist-info/METADATA
autoBoostcamp-10.0.dist-info/WHEEL
autoBoostcamp-10.0.dist-info/top_level.txt
autoBoostcamp-10.0.dist-info/RECORD
